reana_client/__init__.py
reana_client/config.py
reana_client/decorators.py
reana_client/errors.py
reana_client/utils.py
reana_client/version.py
reana_client/api/__init__.py
reana_client/api/client.py
reana_client/cli/__init__.py
reana_client/cli/cwl_runner.py
reana_client/cli/files.py
reana_client/cli/ping.py
reana_client/cli/utils.py
reana_client/cli/workflow.py
reana_client/openapi_connections/reana_server.json
reana_client/schemas/reana_analysis_schema.json
reana_client-0.3.1.dist-info/METADATA
reana_client-0.3.1.dist-info/RECORD
reana_client-0.3.1.dist-info/WHEEL
reana_client-0.3.1.dist-info/entry_points.txt
reana_client-0.3.1.dist-info/top_level.txt
