Metadata-Version: 2.1
Name: reana-client
Version: 0.3.1
Summary: REANA client
Home-page: https://github.com/reanahub/reana-client
Author: REANA
Author-email: info@reana.io
License: UNKNOWN
Platform: UNKNOWN
Classifier: Development Status :: 3 - Alpha
Classifier: Environment :: Console
Classifier: Intended Audience :: Science/Research
Classifier: License :: OSI Approved :: GNU General Public License v2 (GPLv2)
Classifier: Operating System :: OS Independent
Classifier: Programming Language :: Python :: 2
Classifier: Programming Language :: Python :: 2.7
Classifier: Programming Language :: Python :: 3
Classifier: Programming Language :: Python :: 3.6
Classifier: Programming Language :: Python :: 3.7
Classifier: Programming Language :: Python :: Implementation :: CPython
Classifier: Programming Language :: Python
Classifier: Topic :: Internet :: WWW/HTTP :: Dynamic Content
Classifier: Topic :: Software Development :: Libraries :: Python Modules
Provides-Extra: docs
Provides-Extra: all
Provides-Extra: tests
Requires-Dist: bravado (<10.2,>=9.0.6)
Requires-Dist: click (<6.8,>=6.7)
Requires-Dist: cwltool (==1.0.20180912090223)
Requires-Dist: pyOpenSSL (==17.3.0)
Requires-Dist: reana-commons (<0.4,>=0.3.1)
Requires-Dist: rfc3987 (==1.3.7)
Requires-Dist: strict-rfc3339 (==0.7)
Requires-Dist: tablib (<0.13,>=0.12.1)
Requires-Dist: webcolors (==1.7)
Requires-Dist: yadage-schemas (==0.7.16)
Provides-Extra: all
Requires-Dist: Sphinx (>=1.5.1); extra == 'all'
Requires-Dist: sphinx-rtd-theme (>=0.1.9); extra == 'all'
Requires-Dist: sphinx-click (>=1.0.4); extra == 'all'
Requires-Dist: check-manifest (>=0.25); extra == 'all'
Requires-Dist: coverage (>=4.0); extra == 'all'
Requires-Dist: docutils (>=0.14); extra == 'all'
Requires-Dist: httpretty (>=0.8); extra == 'all'
Requires-Dist: isort (>=4.2.2); extra == 'all'
Requires-Dist: pydocstyle (>=1.0.0); extra == 'all'
Requires-Dist: pytest-cache (>=1.0); extra == 'all'
Requires-Dist: pytest-cov (>=1.8.0); extra == 'all'
Requires-Dist: pytest-pep8 (>=1.0.6); extra == 'all'
Requires-Dist: pytest (<3.0.0,>=2.8.0); extra == 'all'
Requires-Dist: Sphinx (>=1.5.1); extra == 'all'
Requires-Dist: sphinx-rtd-theme (>=0.1.9); extra == 'all'
Requires-Dist: sphinx-click (>=1.0.4); extra == 'all'
Requires-Dist: check-manifest (>=0.25); extra == 'all'
Requires-Dist: coverage (>=4.0); extra == 'all'
Requires-Dist: docutils (>=0.14); extra == 'all'
Requires-Dist: httpretty (>=0.8); extra == 'all'
Requires-Dist: isort (>=4.2.2); extra == 'all'
Requires-Dist: pydocstyle (>=1.0.0); extra == 'all'
Requires-Dist: pytest-cache (>=1.0); extra == 'all'
Requires-Dist: pytest-cov (>=1.8.0); extra == 'all'
Requires-Dist: pytest-pep8 (>=1.0.6); extra == 'all'
Requires-Dist: pytest (<3.0.0,>=2.8.0); extra == 'all'
Provides-Extra: docs
Requires-Dist: Sphinx (>=1.5.1); extra == 'docs'
Requires-Dist: sphinx-rtd-theme (>=0.1.9); extra == 'docs'
Requires-Dist: sphinx-click (>=1.0.4); extra == 'docs'
Provides-Extra: tests
Requires-Dist: check-manifest (>=0.25); extra == 'tests'
Requires-Dist: coverage (>=4.0); extra == 'tests'
Requires-Dist: docutils (>=0.14); extra == 'tests'
Requires-Dist: httpretty (>=0.8); extra == 'tests'
Requires-Dist: isort (>=4.2.2); extra == 'tests'
Requires-Dist: pydocstyle (>=1.0.0); extra == 'tests'
Requires-Dist: pytest-cache (>=1.0); extra == 'tests'
Requires-Dist: pytest-cov (>=1.8.0); extra == 'tests'
Requires-Dist: pytest-pep8 (>=1.0.6); extra == 'tests'
Requires-Dist: pytest (<3.0.0,>=2.8.0); extra == 'tests'
